lingualytics/__init__.py
lingualytics/learner.py
lingualytics/preprocessing.py
lingualytics/representation.py
lingualytics/stopwords.py
lingualytics-0.1.3.dist-info/LICENSE
lingualytics-0.1.3.dist-info/METADATA
lingualytics-0.1.3.dist-info/WHEEL
lingualytics-0.1.3.dist-info/top_level.txt
lingualytics-0.1.3.dist-info/RECORD
