Metadata-Version: 2.1
Name: lingualytics
Version: 0.1.3
Summary: A multilingual text analytics package.
Home-page: https://github.com/lingualytics/py-lingualytics
Author: Rohan Rajpal
Author-email: rohan46000@gmail.com
License: MIT
Project-URL: Documentation, https://github.com/lingualytics/py-lingualytics/blob/master/README.md
Project-URL: Source Code, https://github.com/lingualytics/py-lingualytics
Project-URL: Bug Tracker, https://github.com/lingualytics/py-lingualytics/issues
Keywords: text mining,text preprocessing,text representation,text visualization,codemix analytics
Platform: UNKNOWN
Classifier: Development Status :: 3 - Alpha
Classifier: License :: OSI Approved :: MIT License
Classifier: Intended Audience :: Developers
Classifier: Programming Language :: Python
Classifier: Natural Language :: English
Classifier: Topic :: Scientific/Engineering
Requires-Python: >=3.6.1
Requires-Dist: torch (>=1.6)
Requires-Dist: numpy (>=1.17)
Requires-Dist: tabulate (>=0.8.7)
Requires-Dist: pandas (>=1.0.2)
Requires-Dist: transformers (>=3.0)
Requires-Dist: tqdm (>=4.48.2)
Requires-Dist: scikit-learn (>=0.22)
Requires-Dist: texthero (>=1.0)
